{
  "formatVersion": "2",
  "header": {
    "description": "An SAP Fiori application.",
    "originalLanguage": "en",
    "abapLanguageVersion": "cloudDevelopment"
  },
  "generalInformation": {
    "appType": "ui5",
    "catalogId": "SAP_TC_UI5_REPO_UIAD",
    "targetMappingTitle": "Beneflex"
  },
  "ui5AppDetails": {
    "appId": "zrapjmlv"
  },
  "navigation": {
    "targetMappingId": "UI5R_8F88CE0727B39070FFDA6D50411138CBC851BD4D_TM",
    "semanticObject": "Solicitud",
    "action": "Display",
    "desktop": true,
    "tablet": true,
    "phone": true
  },
  "tiles": [
    {
      "id": "UI5R_8F88CE0727B39070FFDA6D50411138CBC851BD4D_AL",
      "tileType": "static",
      "isDefault": true,
      "standard": {
        "title": "Beneflex",
        "subtitle": "Solicitudes Beneflex"
      }
    }
  ]
}
